syncengine/__init__.py
syncengine/_version.py
syncengine/comparator.py
syncengine/concurrency.py
syncengine/config.py
syncengine/constants.py
syncengine/engine.py
syncengine/ignore.py
syncengine/models.py
syncengine/modes.py
syncengine/operations.py
syncengine/pair.py
syncengine/progress.py
syncengine/protocols.py
syncengine/scanner.py
syncengine/state.py
syncengine-0.3.0.dist-info/licenses/LICENSE
syncengine-0.3.0.dist-info/METADATA
syncengine-0.3.0.dist-info/WHEEL
syncengine-0.3.0.dist-info/top_level.txt
syncengine-0.3.0.dist-info/RECORD
